ksos-4.12.1-py3.7-nspkg.pth
kelvin/ksos/__init__.py
kelvin/ksos/ksos.py
ksos-4.12.1.dist-info/METADATA
ksos-4.12.1.dist-info/WHEEL
ksos-4.12.1.dist-info/entry_points.txt
ksos-4.12.1.dist-info/namespace_packages.txt
ksos-4.12.1.dist-info/top_level.txt
ksos-4.12.1.dist-info/zip-safe
ksos-4.12.1.dist-info/RECORD
