Metadata-Version: 2.1
Name: ksos
Version: 4.12.1
Summary: KSOS
Home-page: https://kelvininc.com/
Author: Kelvin Inc
Author-email: engineering@kelvininc.com
Platform: any
Classifier: Operating System :: OS Independent
Classifier: Programming Language :: Python :: 3.7
Classifier: Programming Language :: Python :: 3.8
Classifier: Programming Language :: Python :: 3.9
Classifier: Programming Language :: Python :: 3.10
Requires-Python: <3.11,>=3.7.0
Requires-Dist: click (==8.0.*)
Requires-Dist: kelvin-sdk (==7.12.1)
